README.txt
say_hello.py
setup.py
JWorld.egg-info/PKG-INFO
JWorld.egg-info/SOURCES.txt
JWorld.egg-info/dependency_links.txt
JWorld.egg-info/entry_points.txt
JWorld.egg-info/requires.txt
JWorld.egg-info/top_level.txt
Jworld/__init__.py
Jworld/other_stuff.py